<?xml version="1.0" encoding="UTF-8"?>
<Routine Id="ServiceCode" Version="1">
	<SortedColumn>-1</SortedColumn>
	<SortDirection>0</SortDirection>
	<Column Index="0">
		<Visible>True</Visible>
		<DisplayIndex>0</DisplayIndex>
		<Name>Ordem</Name>
		<Width>70</Width>
	</Column>
	<Column Index="1">
		<Visible>True</Visible>
		<DisplayIndex>1</DisplayIndex>
		<Name>Nome</Name>
		<Width>200</Width>
	</Column>
	<Column Index="2">
		<Visible>True</Visible>
		<DisplayIndex>2</DisplayIndex>
		<Name>Código</Name>
		<Width>200</Width>
	</Column>
	<Column Index="3" ButtonState="Hidden">
		<Visible>False</Visible>
		<DisplayIndex>3</DisplayIndex>
		<Name>Guid</Name>
		<Width>100</Width>
	</Column>
	<Column Index="4" ButtonState="Hidden">
		<Visible>False</Visible>
		<DisplayIndex>4</DisplayIndex>
		<Name>ID</Name>
		<Width>100</Width>
	</Column>
	<Column Index="5">
		<Visible>True</Visible>
		<DisplayIndex>5</DisplayIndex>
		<Name>Criação</Name>
		<Width>100</Width>
	</Column>
	<Column Index="6" ButtonState="Hidden">
		<Visible>False</Visible>
		<DisplayIndex>6</DisplayIndex>
		<Name>Rotina</Name>
		<Width>100</Width>
	</Column>
	<Column Index="7" ButtonState="Hidden">
		<Visible>False</Visible>
		<DisplayIndex>7</DisplayIndex>
		<Name>Salvo</Name>
		<Width>100</Width>
	</Column>
	<Column Index="8" ButtonState="Hidden">
		<Visible>False</Visible>
		<DisplayIndex>8</DisplayIndex>
		<Name>Usuário</Name>
		<Width>100</Width>
	</Column>
</Routine>